[
    {
      "id": "KlIL63MeyMY",
      "thumb": "https://img.youtube.com/vi/KlIL63MeyMY/mqdefault.jpg"
    },
    {
      "id": "aR7CKNFECx0",
      "thumb": "https://img.youtube.com/vi/aR7CKNFECx0/mqdefault.jpg"
    },
    {
      "id":"jFI-qqitzwk",
      "thumb":"https://img.youtube.com/vi/jFI-qqitzwk/mqdefault.jpg"
    },
    {
      "id":"g2x9oyBFSco",
      "thumb":"https://img.youtube.com/vi/g2x9oyBFSco/mqdefault.jpg"
    },
    {
      "id":"ull_DVFFOq0",
      "thumb":"https://img.youtube.com/vi/ull_DVFFOq0/mqdefault.jpg"
    },
    {
      "id":"1wYRGFXpVlg",
      "thumb":"https://img.youtube.com/vi/1wYRGFXpVlg/mqdefault.jpg"
    },
    {
      "id":"GLHbxDU9iBA",
      "thumb":"https://img.youtube.com/vi/GLHbxDU9iBA/mqdefault.jpg"
    }
  ]
  